tesingforfree/__init__.py
tesingforfree-0.0.1.dist-info/LICENCE.txt
tesingforfree-0.0.1.dist-info/METADATA
tesingforfree-0.0.1.dist-info/WHEEL
tesingforfree-0.0.1.dist-info/top_level.txt
tesingforfree-0.0.1.dist-info/RECORD
